{"version":3,"kind":"Article","sha256":"8457ab02f72d9f34f4b771ae6b4dbba7a1186cb2bcb8b46ba2553fcc743114ad","slug":"interacting-with-jupyter-books","location":"/Interacting With Jupyter Books.md","dependencies":[],"frontmatter":{"title":"Working with Jupyter Books","content_includes_title":false,"authors":[{"nameParsed":{"literal":"Financial Python","given":"Financial","family":"Python"},"name":"Financial Python","id":"contributors-myst-generated-uid-0"}],"github":"https://github.com/PatrickJHess/Volume-Three-Chapter-One","copyright":"2025 by the University of Virginia Darden School Foundation, Charlottesville, VA.","numbering":{"title":{"offset":1}},"source_url":"https://github.com/PatrickJHess/Volume-Three-Chapter-One/blob/main/Interacting With Jupyter Books.md","edit_url":"https://github.com/PatrickJHess/Volume-Three-Chapter-One/edit/main/Interacting With Jupyter Books.md","thumbnail":"/Volume-Three-Chapter-One//build/start-button-4a4d2bc9beaa1d76ed508ad0066edc0b.svg","exports":[{"format":"md","filename":"Interacting With Jupyter Books.md","url":"/Volume-Three-Chapter-One//build/Interacting With Jup-95a280f386be49f79ca10ab6bae3becf.md"}]},"mdast":{"type":"root","children":[{"type":"block","children":[{"type":"paragraph","position":{"start":{"line":3,"column":1},"end":{"line":3,"column":1}},"children":[{"type":"text","value":"This and other chapters of ","position":{"start":{"line":3,"column":1},"end":{"line":3,"column":1}},"key":"B4q6SC12hG"},{"type":"emphasis","position":{"start":{"line":3,"column":1},"end":{"line":3,"column":1}},"children":[{"type":"text","value":"Basic Concepts of Fixed Income","position":{"start":{"line":3,"column":1},"end":{"line":3,"column":1}},"key":"Kz1OvcRPkx"}],"key":"KDvc1U0GZD"},{"type":"text","value":", contain two types of documents:","position":{"start":{"line":3,"column":1},"end":{"line":3,"column":1}},"key":"CPpA1dTbzg"}],"key":"vRDX76m8ZN"},{"type":"list","ordered":true,"start":1,"spread":false,"position":{"start":{"line":5,"column":1},"end":{"line":14,"column":1}},"children":[{"type":"listItem","spread":true,"position":{"start":{"line":5,"column":1},"end":{"line":8,"column":1}},"children":[{"type":"paragraph","children":[{"type":"strong","position":{"start":{"line":5,"column":1},"end":{"line":5,"column":1}},"children":[{"type":"text","value":"Markdown documents (","position":{"start":{"line":5,"column":1},"end":{"line":5,"column":1}},"key":"Rh7kGvpZhe"},{"type":"emphasis","position":{"start":{"line":5,"column":1},"end":{"line":5,"column":1}},"children":[{"type":"text","value":".md","position":{"start":{"line":5,"column":1},"end":{"line":5,"column":1}},"key":"OPtyNsH6u4"}],"key":"lXvcDnHmvS"},{"type":"text","value":"):","position":{"start":{"line":5,"column":1},"end":{"line":5,"column":1}},"key":"GfjSpFS62V"}],"key":"h22bKC5cet"}],"key":"avGOPjLNbN"},{"type":"list","ordered":false,"spread":false,"position":{"start":{"line":6,"column":1},"end":{"line":8,"column":1}},"children":[{"type":"listItem","spread":true,"position":{"start":{"line":6,"column":1},"end":{"line":6,"column":1}},"children":[{"type":"paragraph","children":[{"type":"text","value":"What you are currently reading.","position":{"start":{"line":6,"column":1},"end":{"line":6,"column":1}},"key":"YcWOjj5udQ"}],"key":"AIGFxWqCxH"}],"key":"Pjc53QEvhM"},{"type":"listItem","spread":true,"position":{"start":{"line":7,"column":1},"end":{"line":7,"column":1}},"children":[{"type":"paragraph","children":[{"type":"text","value":"Contain no executable code.","position":{"start":{"line":7,"column":1},"end":{"line":7,"column":1}},"key":"CwHe8kjqxS"}],"key":"gSB3WUZ16H"}],"key":"K7qLkDqNqy"},{"type":"listItem","spread":true,"position":{"start":{"line":8,"column":1},"end":{"line":8,"column":1}},"children":[{"type":"paragraph","children":[{"type":"text","value":"Can be downloaded as a Markdown file (","position":{"start":{"line":8,"column":1},"end":{"line":8,"column":1}},"key":"zZpofqfsRp"},{"type":"emphasis","position":{"start":{"line":8,"column":1},"end":{"line":8,"column":1}},"children":[{"type":"text","value":".md","position":{"start":{"line":8,"column":1},"end":{"line":8,"column":1}},"key":"TtcP9YMz00"}],"key":"HUqC7P7i27"},{"type":"text","value":") or a PDF file (","position":{"start":{"line":8,"column":1},"end":{"line":8,"column":1}},"key":"VSaBPTrkHC"},{"type":"emphasis","position":{"start":{"line":8,"column":1},"end":{"line":8,"column":1}},"children":[{"type":"text","value":".pdf","position":{"start":{"line":8,"column":1},"end":{"line":8,"column":1}},"key":"OmhHqyDhcO"}],"key":"zGHLN5uSxW"},{"type":"text","value":").","position":{"start":{"line":8,"column":1},"end":{"line":8,"column":1}},"key":"bJgWpBHSaQ"}],"key":"Py5Ovq0wFC"}],"key":"m7HLyPOL4X"}],"key":"Uxf9yy01es"}],"key":"KiMZOyiURK"},{"type":"listItem","spread":true,"position":{"start":{"line":9,"column":1},"end":{"line":14,"column":1}},"children":[{"type":"paragraph","children":[{"type":"strong","position":{"start":{"line":9,"column":1},"end":{"line":9,"column":1}},"children":[{"type":"text","value":"Notebook documents (","position":{"start":{"line":9,"column":1},"end":{"line":9,"column":1}},"key":"DmBHigLTpj"},{"type":"emphasis","position":{"start":{"line":9,"column":1},"end":{"line":9,"column":1}},"children":[{"type":"text","value":".ipynb","position":{"start":{"line":9,"column":1},"end":{"line":9,"column":1}},"key":"ajWLeyBICY"}],"key":"gwahF7QpKC"},{"type":"text","value":"):","position":{"start":{"line":9,"column":1},"end":{"line":9,"column":1}},"key":"mVkFwCU6so"}],"key":"FJJVYslg1J"}],"key":"HnlpFsNf6h"},{"type":"list","ordered":false,"spread":false,"position":{"start":{"line":10,"column":1},"end":{"line":14,"column":1}},"children":[{"type":"listItem","spread":true,"position":{"start":{"line":10,"column":1},"end":{"line":10,"column":1}},"children":[{"type":"paragraph","children":[{"type":"text","value":"HTML Representations of Jupyter notebooks.","position":{"start":{"line":10,"column":1},"end":{"line":10,"column":1}},"key":"DOERbTCDwN"}],"key":"fakKgd1Nk8"}],"key":"KeBcAdjQpl"},{"type":"listItem","spread":true,"position":{"start":{"line":11,"column":1},"end":{"line":11,"column":1}},"children":[{"type":"paragraph","children":[{"type":"text","value":"Can be downloaded as a notebook (","position":{"start":{"line":11,"column":1},"end":{"line":11,"column":1}},"key":"ZbaO2cGbab"},{"type":"emphasis","position":{"start":{"line":11,"column":1},"end":{"line":11,"column":1}},"children":[{"type":"text","value":".ipynb","position":{"start":{"line":11,"column":1},"end":{"line":11,"column":1}},"key":"tnPCs4juKw"}],"key":"vLdDqagzYy"},{"type":"text","value":") or a PDF file (","position":{"start":{"line":11,"column":1},"end":{"line":11,"column":1}},"key":"eBUMCq0Leq"},{"type":"emphasis","position":{"start":{"line":11,"column":1},"end":{"line":11,"column":1}},"children":[{"type":"text","value":".pdf","position":{"start":{"line":11,"column":1},"end":{"line":11,"column":1}},"key":"MP2A2JuIa7"}],"key":"JrzRRGqidH"},{"type":"text","value":").","position":{"start":{"line":11,"column":1},"end":{"line":11,"column":1}},"key":"Fger3MM4DF"}],"key":"lLa9YomjB6"}],"key":"aR4ELznj61"},{"type":"listItem","spread":true,"position":{"start":{"line":12,"column":1},"end":{"line":12,"column":1}},"children":[{"type":"paragraph","children":[{"type":"text","value":"Have interactive capabilities.","position":{"start":{"line":12,"column":1},"end":{"line":12,"column":1}},"key":"q9uw0Z8yRD"}],"key":"cfdz7geYgH"}],"key":"j1uQwGr7Bd"},{"type":"listItem","spread":true,"position":{"start":{"line":13,"column":1},"end":{"line":14,"column":1}},"children":[{"type":"paragraph","children":[{"type":"text","value":"A notebook can be run inside the HTML file or in binder with Jupyter Lab.","position":{"start":{"line":13,"column":1},"end":{"line":13,"column":1}},"key":"fz1G0VO1GU"}],"key":"klJgEcEDui"}],"key":"Lw3Yz40bu2"}],"key":"vqOVFouuD5"}],"key":"UgL9rdhriX"}],"key":"fQwPTYpSvI"},{"type":"paragraph","position":{"start":{"line":15,"column":1},"end":{"line":15,"column":1}},"children":[{"type":"text","value":"Notebook Launch Options","position":{"start":{"line":15,"column":1},"end":{"line":15,"column":1}},"key":"VKvcCFCm6O"}],"key":"S0cSqIj9oI"},{"type":"paragraph","position":{"start":{"line":17,"column":1},"end":{"line":17,"column":1}},"children":[{"type":"text","value":"There are three interactive options for notebook documents:","position":{"start":{"line":17,"column":1},"end":{"line":17,"column":1}},"key":"WHdp2BJv07"}],"key":"n5Q9NTiPnM"},{"type":"table","position":{"start":{"line":19,"column":1},"end":{"line":23,"column":1}},"children":[{"type":"tableRow","position":{"start":{"line":19,"column":1},"end":{"line":19,"column":1}},"children":[{"type":"tableCell","header":true,"position":{"start":{"line":19,"column":1},"end":{"line":19,"column":1}},"children":[{"type":"text","value":"Option","position":{"start":{"line":19,"column":1},"end":{"line":19,"column":1}},"key":"WV21D7fuT9"}],"key":"RtagG8iMIk"},{"type":"tableCell","header":true,"position":{"start":{"line":19,"column":1},"end":{"line":19,"column":1}},"children":[{"type":"text","value":"Description","position":{"start":{"line":19,"column":1},"end":{"line":19,"column":1}},"key":"cqp4sNpNJW"}],"key":"B5pCOGfjue"},{"type":"tableCell","header":true,"position":{"start":{"line":19,"column":1},"end":{"line":19,"column":1}},"children":[{"type":"text","value":"Interactive Features","position":{"start":{"line":19,"column":1},"end":{"line":19,"column":1}},"key":"lEN3GpIuMs"}],"key":"loegQt7Ioa"},{"type":"tableCell","header":true,"position":{"start":{"line":19,"column":1},"end":{"line":19,"column":1}},"children":[{"type":"text","value":"Note","position":{"start":{"line":19,"column":1},"end":{"line":19,"column":1}},"key":"IjXazOvTsR"}],"key":"ZYxdk80nC9"}],"key":"ER6ujleaqM"},{"type":"tableRow","position":{"start":{"line":21,"column":1},"end":{"line":21,"column":1}},"children":[{"type":"tableCell","position":{"start":{"line":21,"column":1},"end":{"line":21,"column":1}},"children":[{"type":"strong","position":{"start":{"line":21,"column":1},"end":{"line":21,"column":1}},"children":[{"type":"text","value":"Binder","position":{"start":{"line":21,"column":1},"end":{"line":21,"column":1}},"key":"cyYHrX4Ewb"}],"key":"PdMpz2yVt5"}],"key":"OXoz8R6gy0"},{"type":"tableCell","position":{"start":{"line":21,"column":1},"end":{"line":21,"column":1}},"children":[{"type":"text","value":"Launches in a new browser tab (typically within a minute) and runs remotely. Supports up to 100 simultaneous users.","position":{"start":{"line":21,"column":1},"end":{"line":21,"column":1}},"key":"mfxWdQFWS5"}],"key":"zuUT9ybcIM"},{"type":"tableCell","position":{"start":{"line":21,"column":1},"end":{"line":21,"column":1}},"children":[{"type":"text","value":"Execute existing cells, add or modify cells, and download the notebook.","position":{"start":{"line":21,"column":1},"end":{"line":21,"column":1}},"key":"JrBOu4DGE3"}],"key":"CoVBPFROgQ"},{"type":"tableCell","position":{"start":{"line":21,"column":1},"end":{"line":21,"column":1}},"children":[{"type":"text","value":"The notebook will not be saved or available if saved in this mode.","position":{"start":{"line":21,"column":1},"end":{"line":21,"column":1}},"key":"kFXtA4Yd3X"}],"key":"S8WUM5Q6TF"}],"key":"mOmnoRUx0M"},{"type":"tableRow","position":{"start":{"line":22,"column":1},"end":{"line":22,"column":1}},"children":[{"type":"tableCell","position":{"start":{"line":22,"column":1},"end":{"line":22,"column":1}},"children":[{"type":"strong","position":{"start":{"line":22,"column":1},"end":{"line":22,"column":1}},"children":[{"type":"text","value":"Colab","position":{"start":{"line":22,"column":1},"end":{"line":22,"column":1}},"key":"QsqvwVl2PC"}],"key":"fAHp5dV3Re"}],"key":"iD1JfWDIUc"},{"type":"tableCell","position":{"start":{"line":22,"column":1},"end":{"line":22,"column":1}},"children":[{"type":"text","value":"Offers the quickest and easiest access, not requiring Binder. A Google Drive is unnecessary for launching.","position":{"start":{"line":22,"column":1},"end":{"line":22,"column":1}},"key":"kfLPmjUYZh"}],"key":"VpOnNE5vmI"},{"type":"tableCell","position":{"start":{"line":22,"column":1},"end":{"line":22,"column":1}},"children":[{"type":"text","value":"Execute cells or make a copy.","position":{"start":{"line":22,"column":1},"end":{"line":22,"column":1}},"key":"tiQ6PO749U"}],"key":"UfPPqw9Klq"},{"type":"tableCell","position":{"start":{"line":22,"column":1},"end":{"line":22,"column":1}},"children":[{"type":"text","value":"You must sign in to a Google account to execute cells or make a copy. You can download the notebook without signing into a Google account.","position":{"start":{"line":22,"column":1},"end":{"line":22,"column":1}},"key":"S4bMTp9CI7"}],"key":"DJk2lpwcLT"}],"key":"Hw3vtrRNin"},{"type":"tableRow","position":{"start":{"line":23,"column":1},"end":{"line":23,"column":1}},"children":[{"type":"tableCell","position":{"start":{"line":23,"column":1},"end":{"line":23,"column":1}},"children":[{"type":"strong","position":{"start":{"line":23,"column":1},"end":{"line":23,"column":1}},"children":[{"type":"text","value":"Live Code","position":{"start":{"line":23,"column":1},"end":{"line":23,"column":1}},"key":"aupc1014T4"}],"key":"nkmvzFsVf1"}],"key":"v9ZgB6BlgY"},{"type":"tableCell","position":{"start":{"line":23,"column":1},"end":{"line":23,"column":1}},"children":[{"type":"text","value":"Requires a Binder launch and is ideal for demonstrations.","position":{"start":{"line":23,"column":1},"end":{"line":23,"column":1}},"key":"lN81w4ABew"}],"key":"jIty0Q3cuT"},{"type":"tableCell","position":{"start":{"line":23,"column":1},"end":{"line":23,"column":1}},"children":[{"type":"text","value":"Run code in existing cells, and alter code in existing cells.","position":{"start":{"line":23,"column":1},"end":{"line":23,"column":1}},"key":"pLPd5lb3yh"}],"key":"riRkWXSmJl"},{"type":"tableCell","position":{"start":{"line":23,"column":1},"end":{"line":23,"column":1}},"children":[{"type":"text","value":"You cannot add cells or save results in this mode.","position":{"start":{"line":23,"column":1},"end":{"line":23,"column":1}},"key":"gReg1OybfC"}],"key":"pHyaqCDCju"}],"key":"c1Q0nRKLEi"}],"key":"Hg7Mll83dm"},{"type":"paragraph","position":{"start":{"line":26,"column":1},"end":{"line":26,"column":1}},"children":[{"type":"strong","position":{"start":{"line":26,"column":1},"end":{"line":26,"column":1}},"children":[{"type":"text","value":"The start button","position":{"start":{"line":26,"column":1},"end":{"line":26,"column":1}},"key":"ovDf3kYJgb"}],"key":"Ew7t6g2WA5"},{"type":"text","value":" ","position":{"start":{"line":26,"column":1},"end":{"line":26,"column":1}},"key":"ji8A0dRcxG"},{"type":"image","style":{"height":"1.1em","display":"inline-block","verticalAlign":"middle"},"url":"/Volume-Three-Chapter-One//build/start-button-4a4d2bc9beaa1d76ed508ad0066edc0b.svg","alt":"start","key":"OAkpZRRVg0","urlSource":"./start-button.svg"},{"type":"text","value":" ","position":{"start":{"line":26,"column":1},"end":{"line":26,"column":1}},"key":"UNl4bxTgIW"},{"type":"strong","position":{"start":{"line":26,"column":1},"end":{"line":26,"column":1}},"children":[{"type":"text","value":"in a notebook page allows you to execute the code live inside the HTML page.","position":{"start":{"line":26,"column":1},"end":{"line":26,"column":1}},"key":"F8TKIojjyn"}],"key":"eZBZeVP5w0"}],"key":"zjBWRS8fus"},{"type":"paragraph","position":{"start":{"line":28,"column":1},"end":{"line":28,"column":1}},"children":[{"type":"strong","position":{"start":{"line":28,"column":1},"end":{"line":28,"column":1}},"children":[{"type":"text","value":"in a notebook page allows you to execute the code live inside the HTML page.","position":{"start":{"line":28,"column":1},"end":{"line":28,"column":1}},"key":"IRwzE66bLX"}],"key":"uJykd6fxJl"}],"key":"Ttf2t4HxRa"},{"type":"paragraph","position":{"start":{"line":30,"column":1},"end":{"line":30,"column":1}},"children":[{"type":"strong","position":{"start":{"line":30,"column":1},"end":{"line":30,"column":1}},"children":[{"type":"text","value":"The first cell in each notebook includes options to open in Colab or with Jupyter Lab in Binder.","position":{"start":{"line":30,"column":1},"end":{"line":30,"column":1}},"key":"yc9kdBE13t"}],"key":"YeIfamW1ZH"}],"key":"m8c9P9fafv"},{"type":"paragraph","position":{"start":{"line":32,"column":1},"end":{"line":32,"column":1}},"children":[{"type":"text","value":"Additional Interactive Feature","position":{"start":{"line":32,"column":1},"end":{"line":32,"column":1}},"key":"zIeXGAg904"}],"key":"A9mR6RWONi"},{"type":"paragraph","position":{"start":{"line":34,"column":1},"end":{"line":34,"column":1}},"children":[{"type":"strong","position":{"start":{"line":34,"column":1},"end":{"line":34,"column":1}},"children":[{"type":"text","value":"Copying code:","position":{"start":{"line":34,"column":1},"end":{"line":34,"column":1}},"key":"PKpWukSAnL"}],"key":"gH0LwyGdxO"},{"type":"text","value":" Any code cell or code block can be copied to the clipboard by moving the cursor to its upper-right corner.","position":{"start":{"line":34,"column":1},"end":{"line":34,"column":1}},"key":"XNss1SEM4j"}],"key":"Pu8GjwkPed"},{"type":"paragraph","position":{"start":{"line":36,"column":1},"end":{"line":36,"column":1}},"children":[{"type":"text","value":"Summary","position":{"start":{"line":36,"column":1},"end":{"line":36,"column":1}},"key":"JO2ijJoKJW"}],"key":"kTPgtSXngZ"},{"type":"paragraph","position":{"start":{"line":38,"column":1},"end":{"line":38,"column":1}},"children":[{"type":"text","value":"Jupyter books effectively combine Markdown and notebooks to highlight financial concepts with real-world applications.","position":{"start":{"line":38,"column":1},"end":{"line":38,"column":1}},"key":"rxcFRIOprx"}],"key":"DuzVWxM5id"}],"key":"ORn43obbBD"}],"key":"RGcrhFAv5t"},"references":{"cite":{"order":[],"data":{}}},"footer":{"navigation":{"prev":{"title":"Basic Concepts Of Fixed Income: Basic Bond Concepts and the Term Structure of Interest Rates","url":"/","group":"Basic Concepts Of Fixed Income: Basic Bond Concepts and the Term Structure of Interest Rates"},"next":{"title":"Basic Bond Concepts and the Term Structure of Interest Rates","short_title":"Chapter Highlights","url":"/chapter-highlights","group":"Basic Concepts of Fixed Income: Chapter One"}}},"domain":"http://localhost:3013"}